trilobyte/__init__.py
trilobyte/keypoints/__init__.py
trilobyte/keypoints/base_class.py
trilobyte/keypoints/classes.py
trilobyte/keypoints/converters/__init__.py
trilobyte/keypoints/converters/classes.py
trilobyte/trilo/__init__.py
trilobyte/trilo/main.py
trilobyte/utils/__init__.py
trilobyte/utils/helper.py
trilobyte-0.0.1.dist-info/LICENSE
trilobyte-0.0.1.dist-info/METADATA
trilobyte-0.0.1.dist-info/WHEEL
trilobyte-0.0.1.dist-info/top_level.txt
trilobyte-0.0.1.dist-info/RECORD
