Metadata-Version: 2.1
Name: trilobyte
Version: 0.0.1
Summary: Powerful text parsing made intuitive
Home-page: https://github.com/PerceptronV/trilobyte
Author: PerceptronV
Author-email: neutrinovs@gmail.com
License: UNKNOWN
Platform: UNKNOWN
Requires-Python: >=3.3
License-File: LICENSE
